.bumpversion.cfg
.gitignore
LICENSE.txt
Makefile
README.md
VERSION
requirements.txt
setup.py
cbcmgr/__init__.py
cbcmgr/async_pool.py
cbcmgr/cb_bucket.py
cbcmgr/cb_capella.py
cbcmgr/cb_capella_config.py
cbcmgr/cb_collection.py
cbcmgr/cb_connect.py
cbcmgr/cb_connect_lite.py
cbcmgr/cb_connect_lite_a.py
cbcmgr/cb_index.py
cbcmgr/cb_management.py
cbcmgr/cb_operation_a.py
cbcmgr/cb_operation_s.py
cbcmgr/cb_pathmap.py
cbcmgr/cb_rbac.py
cbcmgr/cb_search_index.py
cbcmgr/cb_session.py
cbcmgr/cb_stream_export.py
cbcmgr/cb_transform.py
cbcmgr/config.py
cbcmgr/exceptions.py
cbcmgr/httpsessionmgr.py
cbcmgr/id_format.py
cbcmgr/mt_pool.py
cbcmgr/restmgr.py
cbcmgr/retry.py
cbcmgr/schema.py
cbcmgr/util.py
cbcmgr.egg-info/PKG-INFO
cbcmgr.egg-info/SOURCES.txt
cbcmgr.egg-info/dependency_links.txt
cbcmgr.egg-info/entry_points.txt
cbcmgr.egg-info/requires.txt
cbcmgr.egg-info/top_level.txt
cbcmgr/api/__init__.py
cbcmgr/api/load.py
cbcmgr/cli/__init__.py
cbcmgr/cli/caputil.py
cbcmgr/cli/cbcutil.py
cbcmgr/cli/cli.py
cbcmgr/cli/config.py
cbcmgr/cli/constants.py
cbcmgr/cli/exceptions.py
cbcmgr/cli/exec_step.py
cbcmgr/cli/export.py
cbcmgr/cli/keyformat.py
cbcmgr/cli/main.py
cbcmgr/cli/mptools.py
cbcmgr/cli/pimport.py
cbcmgr/cli/randomize.py
cbcmgr/cli/relational.py
cbcmgr/cli/replicate.py
cbcmgr/cli/schema.py
cbcmgr/cli/sgwutil.py
cbcmgr/cli/system.py
cbcmgr/data/data.json
cbcmgr/data/schema.json
tests/__init__.py
tests/common.py
tests/conftest.py
tests/employee.js
tests/input_stdin.dat
tests/input_template.json
tests/insurance.js
tests/pytest.ini
tests/test_1.py
tests/test_2.py
tests/test_3.py
tests/test_4.py
tests/test_5.py
tests/test_6.py
tests/test_7.py
tests/test_cap_cli.py
tests/test_cli.py
tests/test_m.py
tests/test_m_a.py
tests/test_p.py
tests/test_sgw_cli.py