Metadata-Version: 2.1
Name: cbcmgr
Version: 2.2.33
Summary: Couchbase connection manager
Home-page: https://github.com/mminichino/cb-util
Author: Michael Minichino
Author-email: info@unix.us.com
License: MIT License
Keywords: couchbase,nosql,pycouchbase,database
Classifier: Development Status :: 5 - Production/Stable
Classifier: License :: OSI Approved :: MIT License
Classifier: Intended Audience :: Developers
Classifier: Operating System :: OS Independent
Classifier: Programming Language :: Python
Classifier: Programming Language :: Python :: 3
Classifier: Topic :: Database
Classifier: Topic :: Software Development :: Libraries
Classifier: Topic :: Software Development :: Libraries :: Python Modules
Requires-Python: >=3.8
License-File: LICENSE.txt
Requires-Dist: attrs>=22.2.0
Requires-Dist: couchbase>=4.2.0
Requires-Dist: dnspython>=2.3.0
Requires-Dist: docker>=5.0.3
Requires-Dist: pytest>=7.0.1
Requires-Dist: pytest-asyncio>=0.16.0
Requires-Dist: requests>=2.31.0
Requires-Dist: urllib3>=2.2.1
Requires-Dist: xmltodict>=0.13.0
Requires-Dist: bumpversion>=0.6.0
Requires-Dist: overrides>=7.4.0
Requires-Dist: Jinja2==3.1.2
Requires-Dist: pandas>=1.5.3
Requires-Dist: numpy>=1.24.3
Requires-Dist: Pillow>=8.4.0
Requires-Dist: aiohttp>=3.9.1
Requires-Dist: python-certifi-win32>=1.6.1
Requires-Dist: certifi~=2023.7.22
Requires-Dist: setuptools~=65.5.1
